aptos_sdk_zzf/__init__.py
aptos_sdk_zzf/account.py
aptos_sdk_zzf/account_address.py
aptos_sdk_zzf/account_sequence_number.py
aptos_sdk_zzf/aptos_token_client.py
aptos_sdk_zzf/async_client.py
aptos_sdk_zzf/authenticator.py
aptos_sdk_zzf/bcs.py
aptos_sdk_zzf/ed25519.py
aptos_sdk_zzf/metadata.py
aptos_sdk_zzf/package_publisher.py
aptos_sdk_zzf/transaction_worker.py
aptos_sdk_zzf/transactions.py
aptos_sdk_zzf/type_tag.py
aptos_sdk_zzf-0.7.0.dist-info/METADATA
aptos_sdk_zzf-0.7.0.dist-info/WHEEL
aptos_sdk_zzf-0.7.0.dist-info/RECORD
