Metadata-Version: 2.1
Name: aptos-sdk-zzf
Version: 0.7.0
Summary: Aptos SDK
Home-page: https://github.com/aptos-labs/aptos-core/tree/main/ecosystem/python/sdk
License: Apache-2.0
Keywords: web3,sdk,aptos,blockchain
Author: Aptos Labs
Author-email: opensource@aptoslabs.com
Requires-Python: >=3.8.1,<4.0
Classifier: License :: OSI Approved :: Apache Software License
Classifier: Programming Language :: Python :: 3
Classifier: Programming Language :: Python :: 3.9
Classifier: Programming Language :: Python :: 3.10
Classifier: Programming Language :: Python :: 3.11
Requires-Dist: PyNaCl (>=1.5.0,<2.0.0)
Requires-Dist: h2 (>=4.1.0,<5.0.0)
Requires-Dist: httpx (>=0.24.0,<0.25.0)
Project-URL: Repository, https://github.com/aptos-labs/aptos-core
